poetry_mix/__init__.py
poetry_mix/__itinerary/later.S.HTML
poetry_mix/_clique/__init__.py
poetry_mix/_clique/group/__init__.py
poetry_mix/_licenses/gpl-3.0-standalone.html
poetry_mix/_status/DB/records.json
poetry_mix/_status/monitors/status_1.py
poetry_mix/_status/status.proc.py
poetry_mix/license.S.HTML
poetry_mix/mixer.MD
poetry_mix/mixer.S.HTML
poetry_mix-0.1.1.dist-info/METADATA
poetry_mix-0.1.1.dist-info/WHEEL
poetry_mix-0.1.1.dist-info/entry_points.txt
poetry_mix-0.1.1.dist-info/RECORD
